{
  "cssBase": "default",
  "googleFontsUrl": "https://fonts.googleapis.com/css2?family=IBM+Plex+Sans+Condensed:wght@500;600;700&family=IBM+Plex+Sans:wght@400;500;600&display=swap",
  "font-heading": "'IBM Plex Sans Condensed', sans-serif",
  "font-body": "'IBM Plex Sans', sans-serif",
  "color-bg": "#f2f5f8",
  "color-surface": "#ffffff",
  "color-text": "#16202b",
  "color-muted": "#5c6b7a",
  "color-primary": "#0e5fd8",
  "color-accent": "#ffc224",
  "btn-primary-bg": "#0e5fd8",
  "btn-primary-text": "#ffffff",
  "nav-bg": "#16202b",
  "nav-text": "#f2f5f8",
  "footer-bg": "#16202b",
  "footer-text": "#aebac6",
  "hero-overlay-opacity": "0.55",
  "radius": "6px"
}
