{
  "cssBase": "default",
  "googleFontsUrl": "https://fonts.googleapis.com/css2?family=Outfit:wght@400;500;600;700&family=DM+Sans:ital,wght@0,400;0,500;1,400&display=swap",
  "font-heading": "'Outfit', sans-serif",
  "font-body": "'DM Sans', sans-serif",
  "color-bg": "#0f1115",
  "color-surface": "#181b22",
  "color-text": "#f2f3f5",
  "color-muted": "#9aa1ab",
  "color-primary": "#ffb703",
  "color-accent": "#fb8500",
  "btn-primary-bg": "#ffb703",
  "btn-primary-text": "#14161a",
  "nav-bg": "#0f1115",
  "nav-text": "#f2f3f5",
  "footer-bg": "#0b0d10",
  "footer-text": "#9aa1ab",
  "hero-overlay-opacity": "0.55",
  "radius": "10px"
}
